{
  "$schema": "https://schema.management.azure.com/schemas/2019-04-01/deploymentParameters.json#",
  "contentVersion": "1.0.0.0",
  "parameters": {
    "appName": {
      "value": "test-pensions"
    },
    "appServicePlanName": {
      "value": "pensions"
    },
    "location": {
      "value": "uksouth"
    },
    "sku": {
      "value": "S2"
    },
    "nodeVersion": {
      "value": "20.5.0"
    },
    "runtimeStack": {
      "value": "NODE|20.5.0"
    },
    "port": {
      "value": 3000
    },
    "DOCKER_REGISTRY_SERVER_USERNAME": {
      "value": "pensions"
    },
    "DOCKER_REGISTRY_SERVER_PASSWORD": {
      "value": "xxxx"
    },
    "DOCKER_REGISTRY_SERVER_URL": {
      "value": "https://pensions.azurecr.io"
    },
    "acrName": {
      "value": "pensions"
    }
  }
}
